riskbench_core/__init__.py
riskbench_core/agents/__init__.py
riskbench_core/agents/base.py
riskbench_core/annotator.py
riskbench_core/cli/__init__.py
riskbench_core/dashboard.py
riskbench_core/envs/__init__.py
riskbench_core/envs/base.py
riskbench_core/logging.py
riskbench_core/metrics.py
riskbench_core/monitors/__init__.py
riskbench_core/plugins.py
riskbench_core/recorder.py
riskbench_core/riskmetrics.py
riskbench_core/runner.py
riskbench_core/simulator.py
riskbench_core/taskspec.py
riskbench_suite-0.1.1.dist-info/entry_points.txt
riskbench_suite-0.1.1.dist-info/LICENSE
riskbench_suite-0.1.1.dist-info/METADATA
riskbench_suite-0.1.1.dist-info/WHEEL
riskbench_suite-0.1.1.dist-info/RECORD
